axmp_ai_agent_spec/__init__.py
axmp_ai_agent_spec/profile_base.py
axmp_ai_agent_spec/profile_node_data.py
axmp_ai_agent_spec/types.py
axmp_ai_agent_spec/profiles/a2a_host_agent_profile.py
axmp_ai_agent_spec/profiles/single_agent_profile.py
axmp_ai_agent_spec/profiles/workflow_agent_profile.py
axmp_ai_agent_spec-0.1.6.dist-info/METADATA
axmp_ai_agent_spec-0.1.6.dist-info/WHEEL
axmp_ai_agent_spec-0.1.6.dist-info/entry_points.txt
axmp_ai_agent_spec-0.1.6.dist-info/licenses/LICENSE
axmp_ai_agent_spec-0.1.6.dist-info/RECORD
