Metadata-Version: 2.4
Name: axmp-ai-agent-spec
Version: 0.1.6
Summary: A specification of the AXMP AI Agent attributes and capabilities
Author-email: Kilsoo Kang <kilsoo75@gmail.com>
License-File: LICENSE
Requires-Python: >=3.12
Requires-Dist: croniter>=6.0.0
Requires-Dist: pydantic>=2.11.7
